[{"SM_RackShelf_01": [{"translations": [200.0, 0.0, 37.0], "angles": [0.0, 0.0, 0.0], "sizes": [1.0, 1.0, 1.0]}, {"translations": [600.0, 0.0, 37.0], "angles": [0.0, 0.0, 0.0], "sizes": [1.0, 1.0, 1.0]}, {"translations": [1000.0, 0.0, 37.0], "angles": [0.0, 0.0, 0.0], "sizes": [1.0, 1.0, 1.0]}, {"translations": [1400.0, 0.0, 37.0], "angles": [0.0, 0.0, 0.0], "sizes": [1.0, 1.0, 1.0]}, {"translations": [1800.0, 0.0, 37.0], "angles": [0.0, 0.0, 0.0], "sizes": [1.0, 1.0, 1.0]}, {"translations": [2200.0, 0.0, 37.0], "angles": [0.0, 0.0, 0.0], "sizes": [1.0, 1.0, 1.0]}, {"translations": [2600.0, 0.0, 37.0], "angles": [0.0, 0.0, 0.0], "sizes": [1.0, 1.0, 1.0]}, {"translations": [3000.0, 0.0, 37.0], "angles": [0.0, 0.0, 0.0], "sizes": [1.0, 1.0, 1.0]}]}, {"SM_RackFrame_03": [{"translations": [0.0, 0.0, 0.0], "angles": [0.0, 0.0, 0.0], "sizes": [1.0, 1.0, 1.0]}, {"translations": [400.0, 0.0, 0.0], "angles": [0.0, 0.0, 0.0], "sizes": [1.0, 1.0, 1.0]}, {"translations": [800.0, 0.0, 0.0], "angles": [0.0, 0.0, 0.0], "sizes": [1.0, 1.0, 1.0]}, {"translations": [1200.0, 0.0, 0.0], "angles": [0.0, 0.0, 0.0], "sizes": [1.0, 1.0, 1.0]}, {"translations": [1600.0, 0.0, 0.0], "angles": [0.0, 0.0, 0.0], "sizes": [1.0, 1.0, 1.0]}, {"translations": [2000.0, 0.0, 0.0], "angles": [0.0, 0.0, 0.0], "sizes": [1.0, 1.0, 1.0]}, {"translations": [2400.0, 0.0, 0.0], "angles": [0.0, 0.0, 0.0], "sizes": [1.0, 1.0, 1.0]}, {"translations": [2800.0, 0.0, 0.0], "angles": [0.0, 0.0, 0.0], "sizes": [1.0, 1.0, 1.0]}, {"translations": [0.0, 0.0, 0.0], "angles": [0.0, 0.0, 0.0], "sizes": [1.0, 1.0, 1.0]}, {"translations": [400.0, 0.0, 0.0], "angles": [0.0, 0.0, 0.0], "sizes": [1.0, 1.0, 1.0]}, {"translations": [800.0, 0.0, 0.0], "angles": [0.0, 0.0, 0.0], "sizes": [1.0, 1.0, 1.0]}, {"translations": [1200.0, 0.0, 0.0], "angles": [0.0, 0.0, 0.0], "sizes": [1.0, 1.0, 1.0]}, {"translations": [1600.0, 0.0, 0.0], "angles": [0.0, 0.0, 0.0], "sizes": [1.0, 1.0, 1.0]}, {"translations": [2000.0, 0.0, 0.0], "angles": [0.0, 0.0, 0.0], "sizes": [1.0, 1.0, 1.0]}, {"translations": [2400.0, 0.0, 0.0], "angles": [0.0, 0.0, 0.0], "sizes": [1.0, 1.0, 1.0]}, {"translations": [2800.0, 0.0, 0.0], "angles": [0.0, 0.0, 0.0], "sizes": [1.0, 1.0, 1.0]}, {"translations": [3200.0, 0.0, 0.0], "angles": [0.0, 0.0, 0.0], "sizes": [1.0, 1.0, 1.0]}]}, {"SM_PaletteA_01": [{"translations": [104.04623413085938, 0.0, 37.0], "angles": [0.0, 0.0, 0.0], "sizes": [1.0, 1.0, 1.0]}, {"translations": [482.2792282104492, 0.0, 37.0], "angles": [0.0, 0.0, 0.0], "sizes": [1.0, 1.0, 1.0]}, {"translations": [911.4894409179688, 0.0, 37.0], "angles": [0.0, 0.0, 0.0], "sizes": [1.0, 1.0, 1.0]}, {"translations": [1312.5039825439453, 0.0, 37.0], "angles": [0.0, 0.0, 0.0], "sizes": [1.0, 1.0, 1.0]}, {"translations": [1713.750633239746, 0.0, 37.0], "angles": [0.0, 0.0, 0.0], "sizes": [1.0, 1.0, 1.0]}, {"translations": [2079.5151443481445, 0.0, 37.0], "angles": [0.0, 0.0, 0.0], "sizes": [1.0, 1.0, 1.0]}, {"translations": [2498.907196044922, 0.0, 37.0], "angles": [0.0, 0.0, 0.0], "sizes": [1.0, 1.0, 1.0]}, {"translations": [2907.6520080566406, 0.0, 37.0], "angles": [0.0, 0.0, 0.0], "sizes": [1.0, 1.0, 1.0]}, {"translations": [288.7731170654297, 0.0, 37.0], "angles": [0.0, 0.0, 0.0], "sizes": [1.0, 1.0, 1.0]}, {"translations": [677.8896102905273, 0.0, 37.0], "angles": [0.0, 0.0, 0.0], "sizes": [1.0, 1.0, 1.0]}, {"translations": [1092.4947204589844, 0.0, 37.0], "angles": [0.0, 0.0, 0.0], "sizes": [1.0, 1.0, 1.0]}, {"translations": [1493.0019912719727, 0.0, 37.0], "angles": [0.0, 0.0, 0.0], "sizes": [1.0, 1.0, 1.0]}, {"translations": [1893.6253204345703, 0.0, 37.0], "angles": [0.0, 0.0, 0.0], "sizes": [1.0, 1.0, 1.0]}, {"translations": [2276.5075759887695, 0.0, 37.0], "angles": [0.0, 0.0, 0.0], "sizes": [1.0, 1.0, 1.0]}, {"translations": [2686.203598022461, 0.0, 37.0], "angles": [0.0, 0.0, 0.0], "sizes": [1.0, 1.0, 1.0]}, {"translations": [3090.5760040283203, 0.0, 37.0], "angles": [0.0, 0.0, 0.0], "sizes": [1.0, 1.0, 1.0]}]}, {"SM_CardBoxB_02": [{"translations": [3038.0760040283203, 22.5, 58.0], "angles": [0.0, 0.0, 0.9991481926333556], "sizes": [1.0000000000000004, 1.0000000000000004, 1.0]}, {"translations": [2653.703598022461, 7.5, 58.0], "angles": [0.0, 0.0, 0.5004430161167323], "sizes": [0.9999999999999998, 0.9999999999999998, 1.0]}, {"translations": [1049.9947204589844, 17.5, 58.0], "angles": [0.0, 0.0, 0.6336255064000259], "sizes": [1.0000000000000002, 1.0000000000000002, 1.0]}, {"translations": [2466.407196044922, 7.5, 58.0], "angles": [0.0, 0.0, 0.5004430161167323], "sizes": [0.9999999999999998, 0.9999999999999998, 1.0]}, {"translations": [2022.0151443481445, -37.5, 58.0], "angles": [0.0, 0.0, 0.026156519705001286], "sizes": [1.0, 1.0, 1.0]}]}, {"SM_CardBoxC_01": [{"translations": [3128.0760040283203, 22.5, 58.0], "angles": [0.0, 0.0, 0.6153926088984261], "sizes": [1.0, 1.0, 1.0]}, {"translations": [1841.1253204345703, 7.5, 58.0], "angles": [0.0, 0.0, 0.9094727748280194], "sizes": [0.9999999999999997, 0.9999999999999997, 1.0]}, {"translations": [1530.5019912719727, -7.5, 58.0], "angles": [0.0, 0.0, 0.042466434347857476], "sizes": [1.0, 1.0, 1.0]}, {"translations": [1149.9947204589844, -27.5, 58.0], "angles": [0.0, 0.0, 0.5436683201695383], "sizes": [0.9999999999999999, 0.9999999999999999, 1.0]}, {"translations": [730.3896102905273, -42.5, 58.0], "angles": [0.0, 0.0, 0.6884940864053898], "sizes": [1.0000000000000002, 1.0000000000000002, 1.0]}, {"translations": [2960.1520080566406, -27.5, 58.0], "angles": [0.0, 0.0, 0.5889476128053758], "sizes": [1.0, 1.0, 1.0]}, {"translations": [2127.0151443481445, -42.5, 58.0], "angles": [0.0, 0.0, 0.09457948929837151], "sizes": [0.9999999999999999, 0.9999999999999999, 1.0]}, {"translations": [1661.250633239746, 7.5, 58.0], "angles": [0.0, 0.0, 0.9094727748280194], "sizes": [0.9999999999999997, 0.9999999999999997, 1.0]}, {"translations": [1330.0039825439453, 27.5, 58.0], "angles": [0.0, 0.0, 0.40046443691744565], "sizes": [0.9999999999999999, 0.9999999999999999, 1.0]}, {"translations": [968.9894409179688, -22.5, 58.0], "angles": [0.0, 0.0, 0.7093377798419196], "sizes": [1.0000000000000002, 1.0000000000000002, 1.0]}, {"translations": [534.7792282104492, -42.5, 58.0], "angles": [0.0, 0.0, 0.6884940864053898], "sizes": [1.0000000000000002, 1.0000000000000002, 1.0]}]}, {"SM_CardBoxA_01": [{"translations": [2284.0075759887695, 12.5, 58.0], "angles": [0.0, 0.0, 0.4995220738794465], "sizes": [0.9999999999999999, 0.9999999999999999, 1.0]}, {"translations": [635.3896102905273, -12.5, 58.0], "angles": [0.0, 0.0, 0.969440234399511], "sizes": [1.0000000000000004, 1.0000000000000004, 1.0]}, {"translations": [326.2731170654297, 47.5, 58.0], "angles": [0.0, 0.0, 0.446812553600391], "sizes": [0.9999999999999999, 0.9999999999999999, 1.0]}, {"translations": [2855.1520080566406, -42.5, 58.0], "angles": [0.0, 0.0, 0.043085114910633486], "sizes": [0.9999999999999999, 0.9999999999999999, 1.0]}, {"translations": [439.7792282104492, -12.5, 58.0], "angles": [0.0, 0.0, 0.969440234399511], "sizes": [1.0000000000000004, 1.0000000000000004, 1.0]}, {"translations": [141.54623413085938, 47.5, 58.0], "angles": [0.0, 0.0, 0.446812553600391], "sizes": [0.9999999999999999, 0.9999999999999999, 1.0]}]}, {"SM_CardBoxB_01": [{"translations": [1951.1253204345703, 2.5, 58.0], "angles": [0.0, 0.0, 0.6397853824519747], "sizes": [1.0000000000000002, 1.0000000000000002, 1.0]}, {"translations": [1771.250633239746, 2.5, 58.0], "angles": [0.0, 0.0, 0.6397853824519747], "sizes": [1.0000000000000002, 1.0000000000000002, 1.0]}, {"translations": [868.9894409179688, -42.5, 58.0], "angles": [0.0, 0.0, 0.3747891247193613], "sizes": [0.9999999999999998, 0.9999999999999998, 1.0]}]}, {"SM_CardBoxD_03": [{"translations": [2850.1520080566406, 42.5, 58.0], "angles": [0.0, 0.0, 0.9470655572785885], "sizes": [1.0000000000000002, 1.0000000000000002, 1.0]}, {"translations": [2047.0151443481445, 47.5, 58.0], "angles": [0.0, 0.0, 0.9866949933430108], "sizes": [0.9999999999999996, 0.9999999999999996, 1.0]}]}]